{
	"info": {
		"_postman_id": "6cf03d79-3a01-4dc3-b368-aa8871211971",
		"name": "car-service API",
		"schema": "https://schema.getpostman.com/json/collection/v2.1.0/collection.json"
	},
	"item": [
		{
			"name": "api/external/v1",
			"item": [
				{
					"name": "cars",
					"item": [
						{
							"name": "{id}",
							"item": [
								{
									"name": "/api/external/v1/cars/:id",
									"request": {
										"method": "GET",
										"header": [],
										"url": {
											"raw": "{{baseUrl}}/api/external/v1/cars/:id",
											"host": [
												"{{baseUrl}}"
											],
											"path": [
												"api",
												"external",
												"v1",
												"cars",
												":id"
											],
											"variable": [
												{
													"key": "id",
													"value": "1",
													"description": "(Required) "
												}
											]
										}
									},
									"response": [
										{
											"name": "OK",
											"originalRequest": {
												"method": "GET",
												"header": [],
												"url": {
													"raw": "{{baseUrl}}/api/external/v1/cars/:id",
													"host": [
														"{{baseUrl}}"
													],
													"path": [
														"api",
														"external",
														"v1",
														"cars",
														":id"
													],
													"variable": [
														{
															"key": "id"
														}
													]
												}
											},
											"status": "OK",
											"code": 200,
											"_postman_previewlanguage": "text",
											"header": [
												{
													"key": "Content-Type",
													"value": "text/plain"
												}
											],
											"cookie": [],
											"body": ""
										}
									]
								},
								{
									"name": "/api/external/v1/cars/:id",
									"request": {
										"method": "PUT",
										"header": [
											{
												"key": "Content-Type",
												"value": "application/json"
											}
										],
										"body": {
											"mode": "raw",
											"raw": "{\n    \"name\": \"Audi\",\n    \"price\": 22.33\n}"
										},
										"url": {
											"raw": "{{baseUrl}}/api/external/v1/cars/:id",
											"host": [
												"{{baseUrl}}"
											],
											"path": [
												"api",
												"external",
												"v1",
												"cars",
												":id"
											],
											"variable": [
												{
													"key": "id",
													"value": "1"
												}
											]
										}
									},
									"response": [
										{
											"name": "OK",
											"originalRequest": {
												"method": "PUT",
												"header": [],
												"body": {
													"mode": "raw",
													"raw": "{\n    \"createdAt\": \"<dateTime>\",\n    \"id\": \"<integer>\",\n    \"name\": \"<string>\",\n    \"price\": \"<double>\",\n    \"updatedAt\": \"<dateTime>\"\n}"
												},
												"url": {
													"raw": "{{baseUrl}}/api/external/v1/cars/:id",
													"host": [
														"{{baseUrl}}"
													],
													"path": [
														"api",
														"external",
														"v1",
														"cars",
														":id"
													],
													"variable": [
														{
															"key": "id"
														}
													]
												}
											},
											"status": "OK",
											"code": 200,
											"_postman_previewlanguage": "text",
											"header": [
												{
													"key": "Content-Type",
													"value": "text/plain"
												}
											],
											"cookie": [],
											"body": ""
										}
									]
								},
								{
									"name": "/api/external/v1/cars/:id",
									"request": {
										"method": "DELETE",
										"header": [],
										"url": {
											"raw": "{{baseUrl}}/api/external/v1/cars/:id",
											"host": [
												"{{baseUrl}}"
											],
											"path": [
												"api",
												"external",
												"v1",
												"cars",
												":id"
											],
											"variable": [
												{
													"key": "id",
													"value": "1",
													"description": "(Required) "
												}
											]
										}
									},
									"response": [
										{
											"name": "OK",
											"originalRequest": {
												"method": "DELETE",
												"header": [],
												"url": {
													"raw": "{{baseUrl}}/api/external/v1/cars/:id",
													"host": [
														"{{baseUrl}}"
													],
													"path": [
														"api",
														"external",
														"v1",
														"cars",
														":id"
													],
													"variable": [
														{
															"key": "id"
														}
													]
												}
											},
											"status": "OK",
											"code": 200,
											"_postman_previewlanguage": "text",
											"header": [
												{
													"key": "Content-Type",
													"value": "text/plain"
												}
											],
											"cookie": [],
											"body": ""
										}
									]
								}
							]
						},
						{
							"name": "/api/external/v1/cars",
							"request": {
								"method": "GET",
								"header": [],
								"url": {
									"raw": "{{baseUrl}}/api/external/v1/cars",
									"host": [
										"{{baseUrl}}"
									],
									"path": [
										"api",
										"external",
										"v1",
										"cars"
									]
								}
							},
							"response": [
								{
									"name": "OK",
									"originalRequest": {
										"method": "GET",
										"header": [],
										"url": {
											"raw": "{{baseUrl}}/api/external/v1/cars",
											"host": [
												"{{baseUrl}}"
											],
											"path": [
												"api",
												"external",
												"v1",
												"cars"
											]
										}
									},
									"status": "OK",
									"code": 200,
									"_postman_previewlanguage": "text",
									"header": [
										{
											"key": "Content-Type",
											"value": "text/plain"
										}
									],
									"cookie": [],
									"body": ""
								}
							]
						},
						{
							"name": "/api/external/v1/cars",
							"request": {
								"method": "POST",
								"header": [
									{
										"key": "Content-Type",
										"value": "application/json"
									}
								],
								"body": {
									"mode": "raw",
									"raw": "{\n    \"name\": \"BMW\",\n    \"price\": 123.23\n}"
								},
								"url": {
									"raw": "{{baseUrl}}/api/external/v1/cars",
									"host": [
										"{{baseUrl}}"
									],
									"path": [
										"api",
										"external",
										"v1",
										"cars"
									]
								}
							},
							"response": [
								{
									"name": "OK",
									"originalRequest": {
										"method": "POST",
										"header": [],
										"body": {
											"mode": "raw",
											"raw": "{\n    \"createdAt\": \"<dateTime>\",\n    \"id\": \"<integer>\",\n    \"name\": \"<string>\",\n    \"price\": \"<double>\",\n    \"updatedAt\": \"<dateTime>\"\n}"
										},
										"url": {
											"raw": "{{baseUrl}}/api/external/v1/cars",
											"host": [
												"{{baseUrl}}"
											],
											"path": [
												"api",
												"external",
												"v1",
												"cars"
											]
										}
									},
									"status": "OK",
									"code": 200,
									"_postman_previewlanguage": "text",
									"header": [
										{
											"key": "Content-Type",
											"value": "text/plain"
										}
									],
									"cookie": [],
									"body": ""
								}
							]
						}
					]
				},
				{
					"name": "/api/external/v1/food-using-rest-client/:name",
					"request": {
						"method": "GET",
						"header": [],
						"url": {
							"raw": "{{baseUrl}}/api/external/v1/food-using-rest-client/:name",
							"host": [
								"{{baseUrl}}"
							],
							"path": [
								"api",
								"external",
								"v1",
								"food-using-rest-client",
								":name"
							],
							"variable": [
								{
									"key": "name",
									"value": "biryani",
									"description": "(Required) "
								}
							]
						}
					},
					"response": [
						{
							"name": "OK",
							"originalRequest": {
								"method": "GET",
								"header": [],
								"url": {
									"raw": "{{baseUrl}}/api/external/v1/food-using-rest-client/:name",
									"host": [
										"{{baseUrl}}"
									],
									"path": [
										"api",
										"external",
										"v1",
										"food-using-rest-client",
										":name"
									],
									"variable": [
										{
											"key": "name"
										}
									]
								}
							},
							"status": "OK",
							"code": 200,
							"_postman_previewlanguage": "text",
							"header": [
								{
									"key": "Content-Type",
									"value": "text/plain"
								}
							],
							"cookie": [],
							"body": ""
						}
					]
				}
			]
		}
	],
	"variable": [
		{
			"key": "baseUrl",
			"value": "/",
			"type": "string"
		}
	]
}